{"ID":"bdzcyamh1108","title":"\u9738\u9053\u603b\u88c1\uff1a\u4ee5\u7231\u8c0b\u5a5a","thumb":"https:\/\/minapp.statics.xinghuoyuedu.com\/bdzcyamh1108.jpg","author":"\u590f\u6e05","status":"\u5df2\u5b8c\u7ed3","category":"\u73b0\u4ee3\u8a00\u60c5","read":439988,"summary":"\u201c\u5a36\u6211\uff01\u201d\u5979\u62ff\u4e86\u4e00\u628a\u5200\uff0c\u62b5\u5728\u4ed6\u7684\u80f8\u53e3\u3002\r\n \u7537\u4eba\u90aa\u9b45\u4e00\u7b11\uff0c\u4f38\u624b\u5c06\u5979\u62c9\u8fdb\u81ea\u5df1\u6000\u91cc\uff0c\u201c\u62ff\u4f60\u7684\u8eab\u4f53\u6765\u6362\u2026\u2026\u201d\r\n \u4e8e\u662f\uff0c\u7f20\u7ef5\u60b1\u607b\u2026\u2026\r\n \u5f53\u771f\u76f8\u63ed\u5f00\uff0c\u5979\u624d\u77e5\u9053\uff0c\u4ed6\u6240\u505a\u7684\u4e00\u5207\uff0c\u76ee\u7684\uff0c\u90fd\u662f\u4e3a\u4e86\u5f97\u5230\u5979\u2026\u2026\u6b65\u6b65\u8bf1\u5a5a\uff01","rawid":"gh_702f7db854a3","wxname":"\u4e91\u68a6\u4e66\u697c","wxlink":"http:\/\/wx.jia85.top\/ss\/pdd\/heo4kzer\/towx.png","rawid_b":null,"wxname_b":null,"wxlink_b":null,"enable_abtest":0}