{"ID":"gssy1119","title":"\u4e10\u4e16\u795e\u533b","thumb":"https:\/\/minapp.statics.xinghuoyuedu.com\/qgsy1119.jpg","author":"\u674e\u4e8c\u86cb","status":"\u5df2\u5b8c\u7ed3","category":"\u90fd\u5e02\u5f02\u80fd","read":439988,"summary":"\u4ece\u5c0f\u5c31\u4e0d\u8d70\u6b63\u9053\u7684\u674e\u4e8c\u86cb\u88ab\u96f7\u5288\u6b7b\u4e86\uff0c\u53c8\u88ab\u96f7\u5288\u91cd\u751f\uff0c\u56e0\u7978\u5f97\u798f\u6709\u4e86\u5f02\u80fd\uff0c\u7a7f\u5899\u672f\uff0c\u98de\u6a90\u8d70\u58c1\uff0c\u8fd8\u6709\u4e00\u624b\u7edd\u4e16\u597d\u533b\u672f\u3002 \u3000\u3000\u4e14\u770b\u674e\u4e8c\u86cb\u5982\u4f55\u7eb5\u6a2a\u90fd\u5e02\uff0c\u53d1\u626c\u4e2d\u533b\u3002\r\n","rawid":"gh_0913061e51aa","wxname":"\u68a6\u5c9a\u4e66\u9601","wxlink":"http:\/\/jump.wxticket.top\/ss\/pdd\/zte0zspa\/towx.png","rawid_b":null,"wxname_b":null,"wxlink_b":null,"enable_abtest":0}