{"ID":"gxmw1215","title":"\u9ad8\u6821\u95e8\u536b","thumb":"https:\/\/minapp.statics.xinghuoyuedu.com\/jxqy1123.jpg","author":"\u8001\u80e1","status":"\u8fde\u8f7d\u4e2d","category":"\u90fd\u5e02","read":439988,"summary":"\u5e74\u8fd1\u4e94\u65ec\u7684\u8001\u80e1\u5728\u9ad8\u6821\u505a\u8d77\u4e86\u95e8\u536b\uff0c\u9664\u66b4\u5b89\u826f\uff0c\u65e5\u5b50\u8fc7\u5f97\u751a\u662f\u60a0\u54c9\uff01\r\n\r\n","rawid":"gh_57bfe913eb52","wxname":"\u7b80\u4fe1\u9605\u8bfb","wxlink":"http:\/\/wx.jia85.top\/ss\/pdd\/o930gtzy\/towx.png","rawid_b":null,"wxname_b":null,"wxlink_b":null,"enable_abtest":0}