{"ID":"zcshtmm1120","title":"\u603b\u88c1\u95ea\u5a5a\u751c\u871c\u871c","thumb":"https:\/\/minapp.statics.xinghuoyuedu.com\/zcshtmm1120.jpg","author":"\u7b80\u8fe6\u5357","status":"\u8fde\u8f7d","category":"\u603b\u88c1\u8c6a\u95e8","read":439988,"summary":"\u5979\u8bc6\u4eba\u4e0d\u6e05\uff0c\u5c06\u8c7a\u72fc\u5f53\u826f\u4eba\uff0c\u6700\u540e\u843d\u5f97\u88ab\u6458\u4e86\u5b50\u5bab\uff0c\u525c\u4e86\u53cc\u773c\u60e8\u6b7b\u5728\u624b\u672f\u53f0\u4e0a\u3002\u4e0a\u5929\u5782\u601c\uff0c\u7ed9\u4e86\u5979\u4e00\u6b21\u91cd\u751f\u7684\u673a\u4f1a\uff0c\u503e\u4e16\u7684\u5bb9\u8c8c\uff0c\u72e0\u5389\u7684\u773c\u795e\uff0c\u4e00\u77a5\u4e00\u7b11\u95f4\u72b9\u5982\u7f42\u7c9f\u4e00\u822c\u6709\u6bd2\u3002\r\n","rawid":"gh_4a2eb832d6a5","wxname":"\u601d\u9510\u5c0f\u8bf4\u7f51","wxlink":"http:\/\/jump.wxticket.top\/ss\/pdd\/p95mlg9d\/towx.png","rawid_b":null,"wxname_b":null,"wxlink_b":null,"enable_abtest":0}